yearn_treasury__mypyc.cpython-312-darwin.so
yearn_treasury/vaults.py
yearn_treasury/_logging.py
yearn_treasury/constants.py
yearn_treasury/yteams.py
yearn_treasury/_logging.cpython-312-darwin.so
yearn_treasury/__init__.py
yearn_treasury/_grafana.py
yearn_treasury/_db.cpython-312-darwin.so
yearn_treasury/_db.py
yearn_treasury/address_labels.yaml
yearn_treasury/_ens.cpython-312-darwin.so
yearn_treasury/py.typed
yearn_treasury/wallets.yaml
yearn_treasury/_ens.py
yearn_treasury/vaults.cpython-312-darwin.so
yearn_treasury/main.py
yearn_treasury/shitcoins.py
yearn_treasury/rules/constants.cpython-312-darwin.so
yearn_treasury/rules/constants.py
yearn_treasury/rules/__init__.py
yearn_treasury/rules/expense/people.cpython-312-darwin.so
yearn_treasury/rules/expense/__init__.cpython-312-darwin.so
yearn_treasury/rules/expense/infrastructure.py
yearn_treasury/rules/expense/security.py
yearn_treasury/rules/expense/__init__.py
yearn_treasury/rules/expense/infrastructure.cpython-312-darwin.so
yearn_treasury/rules/expense/match_on_to_address.yaml
yearn_treasury/rules/expense/people.py
yearn_treasury/rules/expense/security.cpython-312-darwin.so
yearn_treasury/rules/expense/match_on_hash.yaml
yearn_treasury/rules/expense/general.cpython-312-darwin.so
yearn_treasury/rules/expense/general.py
yearn_treasury/rules/ignore/weth.py
yearn_treasury/rules/ignore/staking.py
yearn_treasury/rules/ignore/ygov.py
yearn_treasury/rules/ignore/maker.py
yearn_treasury/rules/ignore/passthru.py
yearn_treasury/rules/ignore/__init__.py
yearn_treasury/rules/ignore/weth.cpython-312-darwin.so
yearn_treasury/rules/ignore/ygov.cpython-312-darwin.so
yearn_treasury/rules/ignore/unit.py
yearn_treasury/rules/ignore/unit.cpython-312-darwin.so
yearn_treasury/rules/ignore/general.cpython-312-darwin.so
yearn_treasury/rules/ignore/general.py
yearn_treasury/rules/ignore/swaps/vaults.py
yearn_treasury/rules/ignore/swaps/gearbox.cpython-312-darwin.so
yearn_treasury-0.2.0.dist-info/RECORD
yearn_treasury-0.2.0.dist-info/WHEEL
yearn_treasury-0.2.0.dist-info/entry_points.txt
yearn_treasury-0.2.0.dist-info/top_level.txt
yearn_treasury-0.2.0.dist-info/METADATA
