Metadata-Version: 2.4
Name: yearn_treasury
Version: 0.2.0
Summary: This WIP library runs the eth-portfolio and dao-treasury exporters for the Yearn Finance treasury.
Classifier: Development Status :: 3 - Alpha
Classifier: Intended Audience :: Developers
Classifier: Intended Audience :: Science/Research
Classifier: Intended Audience :: End Users/Desktop
Classifier: Programming Language :: Python :: 3
Classifier: Programming Language :: Python :: 3.10
Classifier: Programming Language :: Python :: 3.11
Classifier: Programming Language :: Python :: 3.12
Classifier: Programming Language :: Python :: Implementation :: CPython
Classifier: Operating System :: OS Independent
Classifier: Topic :: Software Development :: Libraries
Requires-Python: >=3.10,<3.13
Requires-Dist: dao-treasury==1.0.0
Dynamic: classifier
Dynamic: description
Dynamic: description-content-type
Dynamic: requires-dist
Dynamic: requires-python
Dynamic: summary
